dpp_package-0.1.dist-info/DESCRIPTION.rst
dpp_package-0.1.dist-info/METADATA
dpp_package-0.1.dist-info/RECORD
dpp_package-0.1.dist-info/WHEEL
dpp_package-0.1.dist-info/metadata.json
dpp_package-0.1.dist-info/top_level.txt
myPackage/__init__.py
myPackage/pythCode.py
