Metadata-Version: 2.0
Name: dpp-package
Version: 0.1
Summary: Example DPP package
Home-page: https://github.com/dorianwalega96/DPP
Author: Dorian Walega
Author-email: dorianwalega96@gmail.com
License: MIT
Platform: UNKNOWN
